{
  "meta": {
    "slug": "accessibility",
    "currentPath": "/accessibility/",
    "title": "ප් රවේශවීමේ හැකියාව",
    "descriptionKey": "meta.accessibility.description"
  },
  "hero": {
    "eyebrowKey": "hero.accessibility.eyebrow",
    "title": "ප් රවේශවීමේ හැකියාව",
    "lead": "IATF මෙම වෙබ් අඩවිය සරල, කියවිය හැකි, යතුරු පුවරුවෙන් ප් රවේශ විය හැකි සහ සහායක තාක්ෂණයන් සමඟ අනුකූලව තබා ගැනීමට උත්සාහ කරයි.",
    "support": [
      "වෙබ් අඩවි වලට පිවිසීමේ හැකියාව සඳහා, IATF භාවිතා කරයි [W3C WAI](https://www.w3.org/WAI/) ප් රායෝගික ප් රවේශවීමේ හැකියාව සහායක තාක්ෂණයන් භාවිතා කරන්නන්ගේ සෘජු අත්දැකීම් මගින් ද දැනුවත් කරනු ලැබේ."
    ],
    "actions": []
  },
  "report": {
    "header": {
      "kicker": "වාර්තා කිරීම",
      "title": "ප් රවේශවීමේ ගැටලුවක් වාර්තා කරන්න"
    },
    "paragraphs": [
      "ඔබ මෙම වෙබ් අඩවියේ ප් රවේශවීමේ බාධකයක් සොයා ගන්නේ නම්, කරුණාකර එය විද් යුත් තැපෑලෙන් වාර්තා කරන්න:",
      "{{contact.accessibilityEmail}}",
      "ප් රයෝජනවත් වාර්තා අතරට ඇතුළත් වන්නේ:"
    ],
    "items": [
      "ගැටලුව ඇතිවුණු පිටුව",
      "ඔයා කරන්න හදපු දේ",
      "ඔබ භාවිතා කළ උපකාරක තාක්ෂණය, බ් රව්සරය හෝ උපාංගය, අවශ් ය නම්",
      "මොකක්ද වැරැද්ද?",
      "මොනවගේ උදව්වක් වෙයිද?"
    ],
    "footnote": "ඔබට නිල දෝෂ වාර්තාවක් ලිවීමට අවශ් ය නැත. පැහැදිලි විස්තරයක් ප් රමාණවත් වේ."
  },
  "publicIssueHandling": {
    "header": {
      "kicker": "හැසිරවීම",
      "title": "ප් රසිද්ධ ප් රශ්න හසුරුවීම"
    },
    "paragraphs": [
      "ප් රවේශවීමේ ගැටළු අදාළ පොදු ගබඩාවේ සාරාංශ ගත කළ හැකි අතර එමඟින් ඒවා විවෘතව නිවැරදි කළ හැකිය. පුද්ගලික සම්බන්ධතා තොරතුරු සහ අනවශ් ය පුද්ගලික තොරතුරු ප් රකාශයට පත් කිරීමට පෙර ඉවත් කරනු ලැබේ.",
      "ඔබේ වාර්තාවේ පෞද්ගලික තොරතුරු අඩංගු නම්, එය පණිවිඩයේ පැහැදිලිව සඳහන් කරන්න."
    ]
  },
  "knownLimitations": {
    "header": {
      "kicker": "වර්තමාන තත්වය",
      "title": "දන්නා සීමාවන්"
    },
    "paragraphs": [
      "මෙම වෙබ් අඩවිය හිතාමතාම කුඩා වන අතර බොහෝ දුරට ස්ථිතික වේ. සමහර භාෂා අනුවාද පරිවර්තන සකස් කරන අතරතුර අසම්පූර්ණ විය හැකිය."
    ]
  }
}
