{
  "meta": {
    "slug": "propose",
    "currentPath": "/propose/",
    "title": "Қолжетімділік жобасын сұрау",
    "descriptionKey": "meta.propose.description"
  },
  "hero": {
    "eyebrowKey": "hero.propose.eyebrow",
    "title": "Қолжетімділік жобасын сұрау",
    "lead": "IATF нақты қажеттіліктен басталатын қолжетімділік жобалары бойынша өтініштерді қарайды.",
    "support": [
      "Сізге толық сипаттама қажет емес. Кімге әсер ететіні және неге маңызды екендігі туралы нақты мәселе бастау үшін жеткілікті."
    ],
    "actions": [
      {
        "label": "Сұранысты бастау",
        "href": "#request-form",
        "variant": "primary"
      },
      {
        "label": "Оның орнына Discord қолданылсын",
        "href": "{{contact.discordUrl}}",
        "variant": "secondary"
      }
    ]
  },
  "channels": {
    "header": {
      "kicker": "Арналар",
      "title": "Ең оңай жолды таңдаңыз"
    },
    "intro": [
      "Барлық бағыттар бірдей тексеріледі."
    ],
    "items": [
      {
        "label": "Веб-сайт",
        "body": "Құрылымдалған өтінішті беру үшін төмендегі нысанды пайдаланыңыз."
      },
      {
        "label": "Электрондық пошта",
        "body": "Сұрау салуды тікелей {{contact.requestsEmail}}Электрондық пошта арқылы сұрау салулар тексерілгеннен кейін және редакцияланғаннан кейін ашық сұрау жазуларына айналуы мүмкін."
      },
      {
        "label": "Келіспеушілік",
        "body": "Егер оңай болса, сол жерден бастаңыз. Сұраныс әлі де сол қарауға өтеді."
      }
    ]
  },
  "guidance": {
    "title": "Сұрау салуды жібермес бұрын",
    "paragraphs": [
      "IATF қоғамдық түрде жұмыс істейді. Сұранымдар жинақталып, GitHub ұйымында, осы веб-сайтта немесе екеуінде де жария етілуі мүмкін.",
      "Жеке мекен-жайларды, телефон нөмірлерін, медициналық мәліметтерді немесе көмекші технологияларды жеке пайдаланушылар туралы ақпаратты, егер ол қажет болмаса және сіз оны IATF-тің қарауына ыңғайлы болмаса, кіргізбеңіз.",
      "IATF сұраныс деректерін жарияламас бұрын қажетсіз жеке байланыс деректерін алып тастайды."
    ]
  },
  "review": {
    "title": "Қайта қарау күтуі",
    "paragraphs": [
      "Өтінішті беру оның қабылданғанына кепілдік бермейді.",
      "IATF тапсырманың жарамдылығы, жүзеге асырылуы, пайдалылығы және жұмыстың қоғамдық қоймаға жататындығы туралы өтініштерді қарайды.",
      "Кейбір өтініштерді қабылдаудан бұрын қабылдамауы, кейінге қалдыруы немесе қайта құруы мүмкін."
    ]
  },
  "form": {
    "header": {
      "kicker": "Өтініш нысаны",
      "title": "Өтініш беру"
    },
    "fields": [
      {
        "kind": "кіріс",
        "name": "өтініш беруші",
        "label": "Сіздің атыңыз немесе ұйымыңыз",
        "helper": "Мұны кім сұрайды?"
      },
      {
        "kind": "таңдау",
        "name": "Байланыс жолы",
        "label": "Жетілдірілген байланыс бағыты",
        "helper": "Қалай жалғастыру керек?",
        "required": true,
        "options": [
          "Электрондық пошта",
          "Келіспеушілік"
        ]
      },
      {
        "kind": "кіріс",
        "name": "Байланыс мәліметтері",
        "label": "Байланыс деректері",
        "helper": "Ілеспелер үшін электрондық пошта адресі немесе Discord адресі.",
        "placeholder": "Эл. пошта адресі немесе Discord адресі",
        "required": true
      },
      {
        "kind": "кіріс",
        "name": "тіл",
        "label": "Тіл",
        "helper": "Егер қажет болса, таңдаған тіліңіз.",
        "value": "Ағылшынша"
      },
      {
        "kind": "мәтіндік аймақ",
        "name": "мәселе",
        "label": "Қандай мәселені шешуге тырысасыз?",
        "helper": "Тосқауылды қарапайым тілмен сипаттаңыз.",
        "required": true
      },
      {
        "kind": "мәтіндік аймақ",
        "name": "әсер еткен пайдаланушылар",
        "label": "Кімге әсер етеді?",
        "helper": "Бұл кімге көмектеседі?",
        "required": true
      },
      {
        "kind": "мәтіндік аймақ",
        "name": "extra Контекст",
        "label": "Қосымша мәнмәтін",
        "helper": "Қажеттілікті түсіндіруге көмектесетін кез-келген басқа нәрсемен бөлісіңіз: неге маңызды, мысалдар, сілтемелер, бағдарламалық жасақтама идеясы немесе уақыт шектеулері."
      },
      {
        "kind": "таңдау",
        "name": "openSourceConsent-пен келісу",
        "label": "Ашық кодты әзірлеуге ыңғайлысыз ба?",
        "helper": "Қабылданған жобалар IATF бойынша мемлекеттік репозиторийлер болып табылады.",
        "fullWidth": true,
        "required": true,
        "options": [
          "Иә",
          "Жоқ",
          "Әлі белгісіз"
        ]
      }
    ]
  },
  "accepted": {
    "header": {
      "kicker": "Егер қабылданса",
      "title": "Қабылдау дегеніміз не ?"
    },
    "items": [
      "IATF GitHub ұйымының қоғамдық қоймасы",
      "Жобаға тағайындалған жауапты инженер",
      "коды мен жоба материалдарына copyleft лицензиясы",
      "репозиторийдегі қоғамдық даму",
      "IATF сайтындағы тізілім жазбасы"
    ]
  },
  "closing": {
    "header": {
      "kicker": "Сұхбатты бастау",
      "title": "Бастау үшін қысқа, нақты өтініш жеткілікті"
    },
    "paragraphs": [
      "Егер сіз қолжетімділікке мұқтаж болсаңыз және оны қоғамдық жобаға айналдыру керек деп ойласаңыз, бізге жіберіңіз."
    ],
    "actions": [
      {
        "labelKey": "actions.viewProjects",
        "href": "/projects/",
        "variant": "primary"
      },
      {
        "labelKey": "actions.joinDiscord",
        "href": "{{contact.discordUrl}}",
        "variant": "secondary"
      }
    ]
  }
}
