{
  "site.title": "Halkara elýeterlilik iş topary",
  "site.short": "IATF",
  "site.tagline": "Elýeterlilik zerurlygyndan halkara repo",
  "nav.label": "Birinjil",
  "nav.projects": "Gurluşyklar",
  "nav.request": "Talap",
  "nav.join": "Ilkileş",
  "nav.governance": "Hökümdarlyk",
  "nav.transparency": "Açyklyk",
  "nav.github": "GitHub",
  "nav.language": "Dili",
  "nav.languageSingular": "dil",
  "nav.languagePlural": "diller",
  "nav.languageSearch": "Arama dilleri",
  "nav.languageNoMatch": "Oýnaşýanlar ýok",
  "skip.toContent": "Maýdany gaýd et",
  "hero.home.eyebrow": "Açyk Ködli Elýeterlilik",
  "hero.projects.eyebrow": "Halkyň rejestri",
  "hero.propose.eyebrow": "Alynma",
  "hero.governance.eyebrow": "Hökümdarlyk",
  "hero.join.eyebrow": "Gullugyňy dowam et",
  "hero.accessibility.eyebrow": "Elýeterlilik",
  "hero.transparency.eyebrow": "Köpçülik arhiwleri",
  "meta.home.description": "IATF elýeterliligiň hakyky zerurlyklaryny açyk açyk kod depderçelerine öwredýär.",
  "meta.projects.description": "IATF arkaly çap edilen ictimaiy elýeterlilik proyektlerine seret.",
  "meta.propose.description": "IATF-dan web, email, ýa-da Discord arkaly bir elýeterlilik proyektini soraň.",
  "meta.governance.description": "IATF-yň proýektleri kabul edişini, depderleri dolandyryşyny we işiň açyk bolmagyny nädip saklaýandygyny okaň.",
  "meta.join.description": "IATF-a gatnaşmagyň usullary: kod bilen üpjün etmek, terjime etmek, synlamak, ýa-da bir proyekti saklamak.",
  "meta.accessibility.description": "IATF-yň maksady bu web-sayty elýeterli saklamak we elýetmeklik päsgelçiligi barada nädip habar bermek.",
  "meta.transparency.description": "IATF-yň halkara arhiwleri: kararlar, proyektler we täzelemeler açyk goýulýar.",
  "actions.viewProjects": "Ähli proyektleri görkez",
  "actions.proposeProject": "Bir proyekti başla",
  "actions.readGovernance": "Hökümdarlygy okamak",
  "actions.visitGithub": "GitHub-a gidiň",
  "actions.emailProjects": "Projektler poçta gutusy",
  "actions.joinDiscord": "Disord-a goşul",
  "registry.empty.title": "Heniz neşir edilmedik proyektler",
  "registry.empty.body": "IATF ilkinji halkara proýekt toparyny taýýarlaýar.",
  "registry.col.project": "Gurluşyk",
  "registry.col.status": "Durum",
  "registry.col.maintainer": "Garawul diňi",
  "registry.col.repository": "Gaýd etmeklik",
  "registry.col.demo": "Çykgyt",
  "registry.repositoryLabel": "Gaýd etmeklik",
  "registry.demoLabel": "Çykgyt",
  "registry.demoEmpty": "",
  "proposal.form.title": "Talap ýolla",
  "proposal.form.body": "IATF-a soragy ibermek üçin aşakdaky formany dolduryň.",
  "proposal.form.submit": "Talaby ýolla",
  "proposal.form.noscript": "JavaScript bu web formyny ulanmak üçin gerek. Eger ol elýeterli bolmasa, onuň ýerine email ýa-da Discord ullan.",
  "proposal.form.runtimeUnavailable": "Ýaşaýyş ibermek bu meýdançada düzülenok. Bu meýdança siziň elektron poçta klientiniňizi açar.",
  "proposal.form.loadingProtection": "Güýçli girdirmäni taýýarlaýaryn...",
  "proposal.form.ready": "Wezipe taýýar. Talabyňy ibereniňde, IATF bir girişiň ýazgysyny bejerer.",
  "proposal.form.turnstileRequired": "Lütfen ibermezden öň spam goragyny tamamlaň.",
  "proposal.form.turnstileExpired": "Spamdan gorag möhletiniň wagty doldy. Göndermezden öň ýene barlagy tamamlaň.",
  "proposal.form.turnstileError": "Häzirki wagtda spam goragyny barlamak başarmady. Lütfen ýene synanyň.",
  "proposal.form.turnstileTimeout": "Spamdan goragyň wagty doldy. Lütfen barlamagy ýene synanyň.",
  "proposal.form.requiredMessage": "Lütfen ugratmazdan öň talap edilen meýdançalary dolduryň.",
  "proposal.form.submitting": "Dilegi ibermek...",
  "proposal.form.successTitle": "Talap alyndy",
  "proposal.form.success": "Sag boluň. Siziň soragyňyz alyndy we synamak üçin saklandy.",
  "proposal.form.successFollowUp": "Eger siz bu talabyňyz barada ýene-de IATF bilen aralaşsaňyz, aşakdaky baglaýyşy giriň.",
  "proposal.form.successReferenceLabel": "Çykgyt",
  "proposal.form.successRecordLabel": "Alynma ýazgysy",
  "proposal.form.successLinkLabel": "Açyk alnyp barylýan ýazgy",
  "proposal.form.successSummaryTitle": "Nämeler iberildi",
  "proposal.form.reset": "Başga bir soragy iber",
  "proposal.form.errorGeneric": "Talaby iberende bir hata boldy. Lütfen ýene synaniň. Eger mesele dowam etse, ýerine email ulanyň.",
  "proposal.field.required": "Gerekli",
  "proposal.field.optional": "Saýlawly",
  "proposal.field.conditional": "Şertli",
  "proposal.subjectPrefix": "IATF talaby",
  "proposal.subjectUntitled": "Adsyz soraga",
  "project.detail.eyebrow": "Hemme halkara proýekt girişi",
  "project.detail.recordKicker": "Gurluşyk rekordy",
  "project.detail.metadataTitle": "Metadatalar",
  "project.detail.problemTitle": "Bu proýekt nähili kynçylygy çözýär",
  "project.detail.whyTitle": "Näme üçin bu proyekt bar",
  "project.detail.scopeInTitle": "Täzeden seret",
  "project.detail.scopeOutTitle": "Täzeden seretme meýdançasyndan daşda",
  "project.detail.field.status": "Durum",
  "project.detail.field.maintainer": "Garawul diňi",
  "project.detail.field.requestedBy": "Arza bilen:",
  "project.detail.field.license": "Lisans",
  "project.detail.field.repository": "Gaýd etmeklik",
  "project.detail.field.demo": "Çykgyt",
  "project.detail.field.primaryLanguage": "Esasy dil",
  "project.detail.field.languageNotes": "Dil ýazgylary",
  "project.detail.field.lastUpdated": "Soňky täzelenen",
  "project.detail.viewRepository": "Saýlanan faýly gaýd et",
  "project.detail.viewDemo": "Çykgytlary görkez",
  "project.detail.defaultLanguage": "Iňlisçe",
  "project.detail.defaultLanguageNotes": "Adatça iňlisçe çeşme, terjimeler soňra goşulyp biler",
  "footer.label": "Sahypa sözbaşy",
  "footer.linksLabel": "Sahypa barada maglumat",
  "footer.howToContribute": "Nädip goşant goşup bolar",
  "footer.accessibility": "Elýeterlilik",
  "footer.sitemap": "Sahypa nusgasy",
  "footer.licenseContent": "Metin CC BY-SA 4.0",
  "footer.licenseCode": "Kod AGPL-3.0",
  "footer.blurb": "Elýeterlilik işi başlamak, çap etmek we açyk saklamak aňsat bolmaly.",
  "footer.source": "Elýeterlilik standartlary görkezmesi: [W3C WAI](https://www.w3.org/WAI/)Kömekçi tehnologiýa ulanýanlar tarapyndan berilýän maglumatlar.",
  "footer.contactLabel": "Kontak",
  "contact.label": "Kontak",
  "contact.github": "GitHub",
  "contact.discord": "Adalatsyzlyk",
  "project.status.proposal": "Teklip",
  "project.status.accepted": "Kabul edildi",
  "project.status.active": "Aktyw",
  "project.status.stable": "Durnukly",
  "project.status.seeking-maintainer": "Ýolbaşçy gözleýär",
  "project.status.archived": "Arşiw edildi",
  "translation.label": "Çalyşyň haly",
  "translation.source": "Iňlis dili bu sahypanyň kanun dilidir.",
  "translation.humanReviewed": "Bu terjimä akymly gürleýji tarapyndan seredildi.",
  "translation.machineAssisted": "Bu terjime maşyn kömegi bilen edilýär we entek doly täzeden seredilmändir. Täzeden teklipler GitHub arkaly kabul edilýär.",
  "translation.needsUpdate": "Bu terjimäniň iň soňky iňlis dilinde täzeden seredileninden öň barlag geçirilip, düzediş gerek bolmagy mümkin.",
  "translation.report": "Terjime etmek bilen baglanyşykly mesele barada habar ber: {{contact.i18nEmail}}diýip sorady ."
}
