{
  "meta": {
    "slug": "accessibility",
    "currentPath": "/accessibility/",
    "title": "إمكانية الوصول",
    "descriptionKey": "meta.accessibility.description"
  },
  "hero": {
    "eyebrowKey": "hero.accessibility.eyebrow",
    "title": "إمكانية الوصول",
    "lead": "يهدف IATF ليحافظوا على هذا الموقع بسيط، قابل للقراءة، قابل للوصول بواسطة لوحة المفاتيح، و متوافق مع التقنيات المساعدة.",
    "support": [
      "للوصول الى الويب، IATF يستخدم [W3C WAI](https://www.w3.org/WAI/) الوصول العملي يعتمد ايضاً على التجربة المباشرة لمستخدمي التقنيات المساعدة."
    ],
    "actions": []
  },
  "report": {
    "header": {
      "kicker": "تقديم تقارير",
      "title": "ابلغ عن مشكلة الوصول"
    },
    "paragraphs": [
      "لو عثرت على حاجز للوصول على هذا الموقع، ارجوك ابلغ عن طريق البريد الالكتروني:",
      "{{contact.accessibilityEmail}}",
      "تقارير مفيدة تشمل:"
    ],
    "items": [
      "الصفحه اللي حصل فيها المشكلة",
      "ما كنت تحاول ان تفعله",
      "ايش تكنولوجيا المساعدة او المتصفح او الجهاز الذي كنت تستخدمه، اذا لزم الأمر؟",
      "ايش صار غلط؟",
      "ماذا كان سيساعدك؟"
    ],
    "footnote": "ما تحتاجش تكتب تقرير عيب رسمي. وصف واضح كافي."
  },
  "publicIssueHandling": {
    "header": {
      "kicker": "معالجة",
      "title": "معالجة قضايا عامة"
    },
    "paragraphs": [
      "تتم تلخيص مشاكل الوصول في المستودع العام ذي الصلة حتى يتم إصلاحها في العلن. تفاصيل الاتصال الشخصية والمعلومات الخاصة غير الضرورية تتم إزالتها قبل النشر.",
      "لو تقريرك يتضمن معلومات خاصة، قولي هذا بوضوح في الرسالة."
    ]
  },
  "knownLimitations": {
    "header": {
      "kicker": "الوضع الحالي",
      "title": "قيود معروفة"
    },
    "paragraphs": [
      "هذا الموقع صغير عمداً ومثبت في الغالب. بعض النسخ اللغوية قد تكون غير مكتملة بينما يتم تحضير الترجمات."
    ]
  }
}
