[
  {
    "slug": "iatf-website",
    "title": "Sitio web da IATF",
    "summary": "O sitio público da International Accessibility Task Force.",
    "status": "active",
    "maintainer": "mugiwarafx",
    "maintainerUrl": "https://github.com/mugiwarafx",
    "repository": "https://github.com/international-accessibility-task-force/iatf-website",
    "demo": "https://iatf.cc",
    "license": "AGPL-3.0",
    "primaryLanguage": "English",
    "problem": "A IATF necesitaba unha casa pública estable que explicase o modelo, listase proxectos e indique aos contribuíntes o seguinte paso correcto.",
    "why": "O sitio é a porta de entrada pública do IATF. Está construído como un pequeno proxecto estático para que sexa fácil de ler, traducir e manter ao aire libre.",
    "scopeIn": [
      "Páxinas de destino públicas que explican o modelo IATF",
      "Rexistro público de proxectos IATF aceptados, activos e arquivados con estado, mantemento, repositorio e demostración",
      "Páxina e formulario de recepción de solicitudes",
      "Páxinas de gobernanza e transparencia",
      "Fonte en inglés coa estrutura preparada para a tradución",
      "Implementación estática en activos estáticos de traballadores de Cloudflare"
    ],
    "scopeOut": [
      "Áreas privadas de membros, contas ou fluxos de inicio de sesión",
      "Aloxamento do código fonte do proxecto, que vive no propio repositorio de cada proxecto",
      "Chat en tempo real, que vive en Discord",
      "Seguimento de problemas para proxectos individuais, que vive no repositorio GitHub de cada proxecto"
    ]
  },
  {
    "slug": "archived-iatf-selfie",
    "title": "Selfie IATF",
    "summary": "Un prototipo da IATF, arquivado despois de chegar a un punto de parada natural.",
    "status": "archived",
    "maintainer": "mugiwarafx",
    "maintainerUrl": "https://github.com/mugiwarafx",
    "repository": "https://github.com/international-accessibility-task-force/archived-iatf-selfie",
    "license": "Apache-2.0",
    "primaryLanguage": "English",
    "problem": "Exploración precoz dunha ferramenta centrada na accesibilidade no marco da IATF.",
    "why": "O repositorio mantense público como un rexistro do traballo, aínda que o desenvolvemento activo parou.",
    "scopeIn": [
      "Prototipo inicial dunha ferramenta centrada na accesibilidade gardada como rexistro público"
    ],
    "scopeOut": [
      "Desenvolvemento activo ou traballo de características",
      "Compromisos de mantemento",
      "Uso recomendado na produción"
    ]
  },
  {
    "slug": "archived-iatf-bot",
    "title": "IATF bot",
    "summary": "Un bot da comunidade IATF, arquivado despois de chegar a un punto de parada natural.",
    "status": "archived",
    "maintainer": "mugiwarafx",
    "maintainerUrl": "https://github.com/mugiwarafx",
    "repository": "https://github.com/international-accessibility-task-force/archived-iatf-bot",
    "license": "GPL-3.0",
    "primaryLanguage": "English",
    "problem": "Automatización en torno aos canais comunitarios da IATF.",
    "why": "O repositorio mantense público como un rexistro do traballo, aínda que o desenvolvemento activo parou.",
    "scopeIn": [
      "Discord automatización en torno a canles da comunidade IATF, mantido como un rexistro público"
    ],
    "scopeOut": [
      "Desenvolvemento activo ou traballo de características",
      "Compromisos de mantemento",
      "Uso recomendado na produción"
    ]
  }
]
