{
  "meta": {
    "slug": "propose",
    "currentPath": "/propose/",
    "title": "एक्सेसिबिलिटी प्रोजेक्ट के अनुरोध",
    "descriptionKey": "meta.propose.description"
  },
  "hero": {
    "eyebrowKey": "hero.propose.eyebrow",
    "title": "एक्सेसिबिलिटी प्रोजेक्ट के अनुरोध",
    "lead": "IATF उन पहुंच परियोजनाओं के अनुरोधों की समीक्षा करो हय जे एक वास्तविक आवश्यकता से शुरू होवो हय।",
    "support": [
      "आपके पास एक पूर्ण विनिर्देश के लिए कोई आवश्यकता नहीं है। एक स्पष्ट समस्या, यह किस पर प्रभाव डालता है, और यह क्यों महत्वपूर्ण है, शुरू करने के लिए पर्याप्त है।"
    ],
    "actions": [
      {
        "label": "एगो अनुरोध प्रारंभ करबै",
        "href": "#request-form",
        "variant": "primary"
      },
      {
        "label": "एकरा बजाय डिस्कॉर्ड के उपयोग करैं",
        "href": "{{contact.discordUrl}}",
        "variant": "secondary"
      }
    ]
  },
  "channels": {
    "header": {
      "kicker": "चैनलवन",
      "title": "सबसे आसान तरीका अपनाये"
    },
    "intro": [
      "सभे मार्ग एक ही समीक्षा में प्रवेश करो हय।"
    ],
    "items": [
      {
        "label": "वेबसाइट के लेल",
        "body": "एगो संरचित अनुरोध सबमिट करे के लेल नीचे देल गेल फ़ॉर्म के उपयोग कर सकई छी।"
      },
      {
        "label": "ई - मेल से संपर्क करे",
        "body": "अनुरोध सीधे ई पता पर भेजो {{contact.requestsEmail}}. ईमेल अनुरोध समीक्षा और संपादन के बाद सार्वजनिक अनुरोध रिकॉर्ड बन सको हय।"
      },
      {
        "label": "कलह-कलह",
        "body": "अगर ई सबसे आसान हइ, त हुआँ से शुरू करहो । अनुरोध अभी भी वही समीक्षा में चल जा हइ ।"
      }
    ]
  },
  "guidance": {
    "title": "अनुरोध भेजे के पहिले",
    "paragraphs": [
      "IATF सार्वजनिक रूप से काम कर हई। अनुरोध के सारांशित कैल जा सकई हई अउर सार्वजनिक अनुरोध रिकॉर्ड के रूप में प्रकाशित कैल जाए सकई छई, चाहे त आईएटीएफ गिटहब संगठन में, येई वेबसाइट पर, चाहे दुनहु पर।",
      "निजी पते, टेलीफोन नंबर, चिकित्सा विवरण, या सहायक प्रौद्योगिकि के व्यक्तिगत उपयोगकर्ताओं के बारे में पहचान वाला जानकारी शामिल न करे, जब तक कि आवश्यक न हो और आप आईएटीएफ द्वारा एकर समीक्षा करे में सहज न हों।",
      "IATF अनुरोध रिकॉर्ड प्रकाशित करे से पहले अनावश्यक व्यक्तिगत संपर्क विवरण हटा देवो हय।"
    ]
  },
  "review": {
    "title": "समीक्षा अपेक्षाएं",
    "paragraphs": [
      "एगो अनुरोध के प्रस्तुत करनाई स्वीकृति के गारंटी ना देई हई।",
      "IATF मिशन फिट, व्यवहार्यता, उपयोगिता के लिए अनुरोधों की समीक्षा करता है, और क्या काम एक सार्वजनिक रिपॉजिटरी में शामिल है।",
      "कुछ अनुरोध स्वीकृति से पहिले अस्वीकृत, स्थगित या पुनर्गठित कैल जा सको हय।"
    ]
  },
  "form": {
    "header": {
      "kicker": "अनुरोध प्रपत्रवा",
      "title": "एगो अनुरोध करी"
    },
    "fields": [
      {
        "kind": "इनपुट (इनपुट)",
        "name": "आवेदक",
        "label": "अपन नाम या अपन संगठन के नाम",
        "helper": "केकरा द्वारा इ उत्पन करल गेलई हल (लेखन)?"
      },
      {
        "kind": "चुनल गेल",
        "name": "संपर्क रूट",
        "label": "पसंदीदा संपर्क मार्ग",
        "helper": "अनुगमन कैसे करे ?",
        "required": true,
        "options": [
          "ई - मेल से संपर्क करे",
          "कलह-कलह"
        ]
      },
      {
        "kind": "इनपुट (इनपुट)",
        "name": "संपर्क विवरण",
        "label": "संपर्क विवरण",
        "helper": "फॉलो-अप के लिए ईमेल पता या डिस्कॉर्ड पता।",
        "placeholder": "ईमेल पता चाहे डिस्कॉर्ड पता",
        "required": true
      },
      {
        "kind": "इनपुट (इनपुट)",
        "name": "भाषा वाला",
        "label": "भाषा बोलय वालन्",
        "helper": "यदि प्रासंगिक हो, तो आपकी पसंदीदा भाषा।",
        "value": "हंगेरियन"
      },
      {
        "kind": "पाठ क्षेत्र (टेक्स्ट एरिया)",
        "name": "समस्या के हल",
        "label": "कउन समस्या के हल करे के कोशिश कर रहलथिन हँ ?",
        "helper": "सादा भाषा में बाधा के वर्णन करहो।",
        "required": true
      },
      {
        "kind": "पाठ क्षेत्र (टेक्स्ट एरिया)",
        "name": "प्रभावितउपयोगकर्ता",
        "label": "केकरा पर असर होई छई?",
        "helper": "ई केकरा मदत कर सकऽ हइ ?",
        "required": true
      },
      {
        "kind": "पाठ क्षेत्र (टेक्स्ट एरिया)",
        "name": "extraसंदर्भ",
        "label": "अतिरिक्त संदर्भवा",
        "helper": "आवश्यकता के व्याख्या करे में मदद करे वाला कोई अन्य चीज साझा करेंः काहे ई महत्वपूर्ण हई, उदाहरण, संदर्भ, एगो मोटा सॉफ़्टवेयर विचार, चाहे समय सीमा।"
      },
      {
        "kind": "चुनल गेल",
        "name": "openSourceConsent",
        "label": "सार्वजनिक खुला स्रोत विकास के साथ सहज?",
        "helper": "स्वीकृत परियोजना IATF के तहत सार्वजनिक रिपॉजिटरी हय।",
        "fullWidth": true,
        "required": true,
        "options": [
          "हाँ, हइ ।",
          "\"नयँ, नयँ .",
          "अभी तक तो ई बिलकुल पक्का नयँ हइ ।"
        ]
      }
    ]
  },
  "accepted": {
    "header": {
      "kicker": "यदि स्वीकृत हई",
      "title": "स्वीकृति के की अर्थ होवऽ हइ ?"
    },
    "items": [
      "IATF GitHub संगठन में एगो सार्वजनिक रिपॉजिटरी",
      "परियोजना के लिए नामित एक जिम्मेदार इंजीनियर",
      "कोड और परियोजना सामग्री के लिए एक कॉपीलेफ्ट लाइसेंस",
      "रिपॉजिटरी में सार्वजनिक विकास",
      "IATF साइट पर एगो रजिस्टर प्रविष्टि"
    ]
  },
  "closing": {
    "header": {
      "kicker": "बातचीत शुरू करे",
      "title": "एक छोटा, स्पष्ट अनुरोध शुरू करे के लिए पर्याप्त है"
    },
    "paragraphs": [
      "अगर आपके पास वास्तव में एक सुलभता आवश्यकता है और आपको लगता है कि यह एक सार्वजनिक परियोजना होनी चाहिए, तो हमे भेजो।"
    ],
    "actions": [
      {
        "labelKey": "actions.viewProjects",
        "href": "/projects/",
        "variant": "primary"
      },
      {
        "labelKey": "actions.joinDiscord",
        "href": "{{contact.discordUrl}}",
        "variant": "secondary"
      }
    ]
  }
}
