{
  "meta": {
    "slug": "governance",
    "currentPath": "/governance/",
    "title": "शासन अउ भंडारण मॉडल",
    "descriptionKey": "meta.governance.description"
  },
  "hero": {
    "eyebrowKey": "hero.governance.eyebrow",
    "title": "शासन अउ भंडारण मॉडल",
    "lead": "आईएटीएफ अभिगम्यता परियोजनाओं ल सार्वजनिक, पठनीय, अउ रखरखाव योग्य रखत हवय।",
    "support": [
      "ए पृष्ठ बतात हवय कि काय अर्हता प्राप्त करत हवय , रिपॉजिटरी ल कैले आयोजित करे जात हवय , अउ स्वीकृति के पाछू रिपोजिटरी स्तर के जिम्मेदारी काय लागू होत हवय ।"
    ],
    "actions": [
      {
        "labelKey": "actions.proposeProject",
        "href": "/propose/",
        "variant": "primary"
      },
      {
        "labelKey": "actions.viewProjects",
        "href": "/projects/",
        "variant": "secondary"
      }
    ]
  },
  "baseline": {
    "header": {
      "kicker": "नियममन",
      "title": "मिशन फिट, स्वामित्व, लाइसेंसिंग"
    },
    "cards": [
      {
        "title": "मिशन फिट करे",
        "paragraphs": [
          "आईएटीएफ ओ काम ल स्वीकार करत हवय जेहर एक वास्तविक अभिगम्यता बाधा ल संबोधित करत हवय अउ स्पष्ट सार्वजनिक मूल्य हवय।",
          "एक परियोजना ल एकठन निजी वर्कफ़्लो ले बाहीर उपयोगी होना चाहि अउ सार्वजनिक रिपॉजिटरी के रूप म काम करे योग्य होना चाहि ।",
          "वेब सुलभता बर , आईएटीएफ उपयोग करत हवय [W3C WAI](https://www.w3.org/WAI/) सहायक प्रौद्योगिकिमन के उपयोगकर्ताओं के प्रत्यक्ष अनुभव घलो वास्तविक उपयोग में काय काम करत हवय के व्यावहारिक सबूत हवय।"
        ]
      },
      {
        "title": "परियोजना के स्वीकृति",
        "paragraphs": [
          "एक प्रस्ताव ल स्वीकार करे जा सकत हवय जब समीक्षा बतात हवय कि:"
        ],
        "items": [
          "ए एक वास्तविक अभिगम्यता आवश्यकता ल संबोधित करत हवय ।",
          "समस्या मूल्यांकन करे बर म पर्याप्त रूप ले स्पष्ट हवय",
          "स्कोप लॉन्च करे बर म पर्याप्त यथार्थवादी हवय",
          "काम आईएटीएफ मिशन के साथ संरेखित होत हवय",
          "रखरखाव या पूरा करे बर एक प्रशंसनीय पथ हवय।"
        ]
      },
      {
        "title": "रिपॉजिटरी स्वामित्व",
        "paragraphs": [
          "स्वीकृत परियोजनामन के आईएटीएफ गिटहब संगठन के तहत बनइन जात हवय ।",
          "रिपॉजिटरी उहां रहत हवयं ताकि प्रत्येक परियोजना एकठन स्थिर सार्वजनिक घर रख सकय , भले ही रखरखावकर्ता पाछू म बदल जात हवयं।"
        ]
      },
      {
        "title": "लाइसेंसिंग करे",
        "paragraphs": [
          "आईएटीएफ प्रोजेक्ट कॉपीलेफ्ट लाइसेंसिंग के उपयोग करत हंवय जब तक कि एकठन प्रोजेक्ट आने रहिस:"
        ],
        "items": [
          "<strong>कोडः अउ</strong> एजीपीएल-3.0",
          "<strong>प्रलेखन:</strong> सीबीआई-एसए 4.0 के तहत उपयोग बर"
        ]
      }
    ]
  },
  "operations": {
    "maintainer": {
      "title": "जिम्मेदार इंजीनियर या रखरखावकर्ता",
      "paragraphs": [
        "प्रत्येक स्वीकृत परियोजना में एक नामित जिम्मेदार इंजीनियर या रखरखावकर्ता होना चाहि। ओ व्यक्ति ल भंडार तक प्रशासनिक पहुंच मिल सकत हवय अउ एहर अपेक्षित हवय:"
      ],
      "items": [
        "सार्वजनिक म विकास गाइड",
        "रिपॉजिटरी संरचना बनाए रखे",
        "मुद्दामन के समीक्षा या प्रबंधित करव अउ अनुरोध ल खींचव",
        "महत्वपूर्ण तकनीकी निर्णयों का दस्तावेजीकरण करे",
        "परियोजना ल दूसरमन बर समझने योग्य बनावव"
      ],
      "footnote": "ए रिपॉजिटरी स्तर के जिम्मेदारी हवय। संगठनात्मक स्वामित्व आईएटीएफ के साथ रहत हवय। जिम्मेदारी इहां रिपोजिटरी स्टीयर्डशिप, तकनीकी दिशा, अउ सार्वजनिक समन्वय हवय  सार्वजनिक रोडमैप के बाहीर असीमित निजी डिलीवरी, कस्टम एकीकरण, या सेवा स्तर के प्रतिबद्धता नी हवय।"
    },
    "publicDevelopment": {
      "title": "सार्वजनिक विकास करे",
      "paragraphs": [
        "आईएटीएफ के माध्यम ले शुरू करे गए परियोजनामन ल डिफ़ॉल्ट रूप ले सार्वजनिक रूप ले विकसित करे जात हवय । रिपॉजिटरी सत्य के सार्वजनिक स्रोत हवय:"
      ],
      "items": [
        "स्रोत कोड अउ",
        "मुद्दामन",
        "प्रलेखन",
        "रोडमैप नोट्स",
        "रिलीज़ इतिहास"
      ],
      "footnote": "महत्वपूर्ण परियोजना ज्ञान केवल निजी चैट या इनबॉक्स म नी रहना चाहि।"
    }
  },
  "requestRecords": {
    "header": {
      "kicker": "सार्वजनिक रिकॉर्ड्स",
      "title": "सार्वजनिक अनुरोध रिकॉर्ड्स"
    },
    "paragraphs": [
      "आईएटीएफ डिफ़ॉल्ट रूप ले सार्वजनिक रूप ले काम करत हवय । अनुरोध जेहर वेबसाइट, ईमेल, डिस्कॉर्ड, गिटहब, या आने आईएटिएफ चैनल के माध्यम ले आईटीएफ में प्रवेश करत हंवय , सार्वजनिक अनुरोध रिकॉर्ड बन सकत हंवय ।",
      "एक सार्वजनिक अनुरोध रिकॉर्ड मूल संदेश नी होए । आईएटीएफ प्रकाशन ले पहीली एक अनुरोध के सारांशित, संपादित, या पुनर्गठन कर सकत हवय ताकि अनावश्यक व्यक्तिगत जानकारी के उजागर करे के बिना अभिगम्यता के आवश्यकता के समीक्षा करे जा सके ।",
      "सार्वजनिक अनुरोध रिकॉर्ड IATF GitHub संगठन, ए वेबसाइट म, या दोनों म संग्रहीत करे जा सकत हवय ।",
      "प्रकाशन ले पहीली, आईएटीएफ अनावश्यक व्यक्तिगत संपर्क विवरण, निजी पते, अउ सहायक प्रौद्योगिकिमन के व्यक्तिगत उपयोगकर्ताओं के बारे में पहचान विवरणों ल हटा देत हवय जब तक कि प्रकाशन स्पष्ट रूप ले इरादा अउ उपयुक्त नी होत हवय।",
      "असहमति के उपयोग अनौपचारिक समन्वय बर करे जात हवय । आईएटीएफ डिफ़ॉल्ट रूप ले अलग-अलग डिस्कॉर्ड वार्तालापों ल संग्रहीत नी करत हवय , अउ संदेश प्रतिधारण के नियंत्रण डिसॉर्ड द्वारा करिस जात हवय। डिसॉर्ड म करे गए फैसलों ल गिटहब या संबंधित परियोजना पृष्ठ म सार्वजनिक रिकॉर्ड म सारांशित करे जाना चाहि ।",
      "अनुरोध रिकॉर्ड ल तकनीकी रूप ले व्यावहारिक खोज इंजन अनुक्रमण ले बाहीर रखे जात हवय । सार्वजनिक के मतलब समीक्षा योग्य अउ जवाबदेह हवय । एखर मतलब ए नी हवय कि नाम खोज के माध्यम ले खोज बर अनुकूलित करे गय हवय ।",
      "आईएटीएफ सार्वजनिक सतहों ले रिकॉर्ड्स ल अपडेट या हटा सकत हवय, लेकिन तीसरे पक्ष के कैश, अधिसूचना, कांटा, स्क्रीनशॉट, खोज इंजन, डिस्कॉर्ड, या आने बाहरी सिस्टम ले हटाने के गारंटी नी दे सकत हवय।",
      "यदि संदेश ल निजी बने रहना चाहि, त एला आईएटीएफ सार्वजनिक चैनल के माध्यम ले झन भेजव।"
    ]
  },
  "chair": {
    "header": {
      "kicker": "संगठनात्मक भूमिका",
      "title": "अध्यक्षता करे"
    },
    "lead": "एहर प्रति-परियोजना जिम्मेदार इंजीनियर के भूमिका ले अलग हवय: अध्यक्ष पूरे संगठन बर जिम्मेदार हवय, न कि काखरो घलो रिपॉजिटरी के दिन-प्रतिदिन के दिशा बर।",
    "duties": {
      "title": "कुर्सी काय करत हवय",
      "items": [
        "IATF GitHub संगठन म मालिक अनुमतियां रखत हवय",
        "परियोजना स्वीकृति अउ अभिलेखीय निर्णय म हस्ताक्षर",
        "आईएटीएफ बर सार्वजनिक संपर्क बिंदु के रूप म कार्य करत हवय",
        "वार्षिक चुनाव के समन्वय करथे"
      ],
      "footnote": "अध्यक्ष निजी डिलीवरी, सशुल्क काम, या सेवा स्तर के समझौतों बर IATF ल बाध्य नी करत हवय , अउ तकनीकी निर्देशन म प्रति रिपॉजिटरी रखरखावकर्ता के फैसलों ल ओवरराइड नी करत हंवय ।"
    },
    "election": {
      "title": "वार्षिक चुनाव",
      "paragraphs": [
        "अध्यक्ष के चुनाव एक साल म एक बार करे जात हवय। चुनाव दिसंबर के पहीली दो हफ्तों म चलत हवय, परिणाम 15 दिसंबर तक घोषित करे जात हवयं, अउ नवा कार्यकाल 1 जनवरी ले शुरू होत हवय ।",
        "पात्र मतदाता ओ मनखे हवयं जेहर वर्ष के दौरान काखरो घलो आईएटीएफ रिपॉजिटरी म मर्मतकर्ता भूमिका निभाए हवयं अउ ओ वर्ष म कम ले कम एकठन मर्ज किए गए योगदान दिए हवयं। प्रत्येक योग्य मतदाता के पास एक वोट हवय । सबले ज्यादा वोट वाला उम्मीदवार जीतता हवय; टाई के मामले म , एक रनऑफ दिसम्बर के तीसरे सप्ताह म आयोजित करे जात हवय ।",
        "चुनाव ल निर्दिष्ट आईएटीएफ शासन रिपॉजिटरी म एक सार्वजनिक गिटहब चर्चा के रूप म संचालित करे जात हवय , एखरबर उम्मीदवार, मतदान, अउ म परिणाम सार्वजनिक रिकॉर्ड के जम्मो हिस्सा हवयं।"
      ]
    },
    "continuity": {
      "title": "निरंतरता",
      "paragraphs": [
        "यदि काखरो दिए गए वर्ष म कोई चुनाव नी होए , त वर्तमान अध्यक्ष अगले चुनाव तक भूमिका म रहता हवय । ए एकठन अनिश्चितकालीन निरंतरता हवय , एकठन अनुग्रह अवधि नी  मॉडल ल संगठन ल स्थिर रखे बर डिज़ाइ करे गय हवय जब गतिविधि कम होत हवय , न कि एकठन संक्रमण ल मजबूर करे बर जेहर कन्हु तैयार नी होए ।",
        "अध्यक्ष काखरो घलो समय इस्तीफा दे सकत हवय। सक्रिय रखरखावकर्ता एकठन घोषित कारण के साथ एक असाधारण चुनाव घलो कॉल कर सकत हवयं, जेहर वार्षिक चुनाव के समान नियममन के तहत संचालित होत हवयं।"
      ]
    },
    "current": {
      "title": "वर्तमान अध्यक्ष",
      "fields": [
        {
          "label": "अध्यक्षता करे",
          "value": "मुगियाराफैक्स",
          "href": "https://github.com/mugiwarafx"
        },
        {
          "label": "अवधि (टर्म)",
          "value": "दिसंबर 2026 के चुनाव तक"
        },
        {
          "label": "भूमिका औपचारिक रूप ले",
          "value": "2026"
        },
        {
          "label": "पहिली अनुसूचित चुनाव",
          "value": "दिसम्बर 2026"
        }
      ]
    },
    "footnote": "तब तक, संगठनात्मक जिम्मेदारी संस्थापक द्वारा अनौपचारिक रूप ले आयोजित के गइस रहिस ।"
  },
  "continuity": {
    "states": {
      "title": "परियोजना के स्थिति",
      "paragraphs": [
        "परियोजना सार्वजनिक राज्यों के एक छोटे लेट का उपयोग करत हवय:"
      ],
      "items": [
        "प्रस्ताव हवय",
        "स्वीकार करे",
        "सक्रिय करे",
        "स्थिर हवय",
        "रखरखावकर्ता खोजत हवय",
        "अभिलेखागार म"
      ],
      "footnote": "इ राज्यमन रजिस्ट्री ल स्कैन करे बर आसान रखत हंवय ।"
    },
    "reassignment": {
      "title": "पुनर्निर्धारण अउ अभिलेखागार",
      "paragraphs": [
        "यदि कोई रखरखावकर्ता कदम उठात हवय या निष्क्रिय हो जात हवय , तो आईएटीएफ जिम्मेदारी ल फिर ले सौंप सकत हवय , विकास ल रोक सकत हवय या परियोजना ल संग्रहीत कर सकत हवय ।",
        "एक परियोजना ल अभिलेखागार घलो करे जा सकत हवय जब मूल आवश्यकता पूरा हो गए हवय, रखरखाव बंद हो गय हवय, या जारी काम अब यथार्थवादी नी हवय।"
      ],
      "footnote": "अभिलेखीय परियोजना सार्वजनिक रूप ले दृश्यमान रहत हवयं जब तक कि अन्यथा करे बर कोई बाध्यकारी कारण नी होए ।"
    }
  },
  "boundaries": {
    "header": {
      "kicker": "सीमा नोट",
      "title": "आईएटीएफ का काय गारंटी नी हवय"
    },
    "items": [
      "निजी क्लाइंट डिलीवरी",
      "सर्विस लेवल एग्रीमेंट्स",
      "हर प्रस्ताव के स्वीकृति",
      "हर परियोजना बर दीर्घकालिक रखरखाव"
    ],
    "footnote": "आईएटीएफ एक सार्वजनिक रिपॉजिटरी मॉडल हवय , न कि एकठन निजी डिलीवरी सेवा।"
  }
}
